{
    "news_source": "nasdaq",
    "news_id": "nasdaq_52e82934e1b2",
    "news_header": "Fidelity Select Health Care (FSPHX) is being evaluated as a strong mutual fund option currently, based on its performance and market conditions.",
    "news_original_title": "Is Fidelity Select Health Care (FSPHX) a Strong Mutual Fund Pick Right Now?",
    "news_text": "",
    "news_url": "https://www.nasdaq.com/articles/fidelity-select-health-care-fsphx-strong-mutual-fund-pick-right-now-0",
    "news_time": 1739440800.0,
    "news_categories": [
        "business",
        "tech"
    ],
    "news_source_lang": "en",
    "news_group": -1
}