{
    "news_source": "bbc",
    "news_id": "bbc_czdl6d0r2g5o",
    "news_header": "The UN peacekeeping force in Lebanon reported that its outgoing deputy commander was injured in a violent attack on a convoy transporting peacekeepers to Beirut airport.",
    "news_original_title": "Senior UN peacekeeper injured in convoy attack in Lebanon",
    "news_text": "The attack occurred amid protests blocking the airport road due to the Lebanese government&#x27;s decision to prevent two Iranian planes from landing. Lebanese officials condemned the attack, calling for justice against the perpetrators. Videos showed the convoy being attacked by protesters, with one UN vehicle set on fire. The incident has raised concerns about the safety of peacekeepers in the region.",
    "news_url": "https://www.bbc.com/news/articles/czdl6d0r2g5o",
    "news_time": 1739597760.0,
    "news_categories": [
        "world"
    ],
    "news_source_lang": "en",
    "news_group": 342
}