{
    "news_source": "yle",
    "news_id": "yle_7420143195",
    "news_header": "Nordnet&#x27;s mobile application and website experienced issues due to a malfunctioning software component related to login, not a hacker attack. This caused some customers to see inaccurate account information and allowed trading of other users&#x27; securities, but funds could not be transferred. Nordnet closed its services for several hours to address the problem and is now assessing the impact on affected customers.",
    "news_original_title": "Ainakin yhden Nordnetin asiakkaan tilill\u00e4 joku muu yritti tehd\u00e4 kauppaa",
    "news_text": "The company has apologized and is taking steps to prevent future incidents. Their share price fell by 6% but slightly recovered the following day.",
    "news_url": "https://yle.fi/a/74-20143195",
    "news_time": 1739342520.0,
    "news_categories": [
        "business"
    ],
    "news_source_lang": "en",
    "news_group": -1
}