{
    "news_source": "yle",
    "news_id": "yle_7420143736",
    "news_header": "Google has renamed the Gulf of Mexico to the Gulf of America on its maps, following a directive from President Donald Trump. The company has also restricted negative reviews for the Gulf of Mexico in its map services.",
    "news_original_title": "Google esti ihmisi\u00e4 antamasta huonoja arvioita Meksikonlahdelle karttapalvelussaan",
    "news_text": "This change has led users to express their dissatisfaction by leaving one-star reviews for Google Maps in Apple&#x27;s app store, a form of online protest known as review bombing.",
    "news_url": "https://yle.fi/a/74-20143736",
    "news_time": 1739522100.0,
    "news_categories": [
        "world"
    ],
    "news_source_lang": "en",
    "news_group": 297
}