{
    "news_source": "dw",
    "news_id": "dw_a71251164",
    "news_header": "Elon Musk's influence in the global satellite sector is growing, with Italy negotiating a \u20ac1.6 billion deal with SpaceX for Starlink services, raising national security concerns.",
    "news_text": "As Elon Musk's influence in European politics grows, Italy is in advanced negotiations with SpaceX for a \u20ac1.6 billion deal for Starlink satellite services. This has sparked controversy, with opposition accusing Prime Minister Giorgia Meloni of compromising national security. Experts believe such deals will become common due to Starlink's reliable services. Musk's growing power in the satellite sector raises concerns about geopolitical security, especially regarding his potential to influence government communications.",
    "news_url": "https://www.dw.com/en/elon-musk-s-starlink-talks-with-italy-raise-concerns/a-71251164",
    "news_time": 1736413620.0,
    "news_categories": [
        "business"
    ],
    "news_source_lang": "en",
    "news_group": -1
}