{
    "news_source": "dw",
    "news_id": "dw_a70453644",
    "news_header": "Maxime Labrit pyrkii mullistamaan miesten ehk\u00e4isyn ja puuttumaan miesten vaihtoehtojen puutteeseen ja naisiin kohdistuvaan tahattomien raskauksien taakkaan.",
    "news_text": "Maxime Labrit esittelee Pariisissa j\u00e4rjestetyss\u00e4 lis\u00e4\u00e4ntymisoikeustapahtumassa v\u00e4rikk\u00e4it\u00e4 silikonirenkaita, joiden tarkoituksena on mullistaa miesten ehk\u00e4isy. Koska maailmassa on yli 2 miljardia siitti\u00f6it\u00e4 tuottavaa yksil\u00f6\u00e4 ja tahattomien raskauksien m\u00e4\u00e4r\u00e4 on suuri, Labrit korostaa, ett\u00e4 miesten ehk\u00e4isyvaihtoehtoja on lis\u00e4tt\u00e4v\u00e4. Nykyisi\u00e4 edistysaskeleita ovat hormonaaliset tuotteet, kuten NES/T-geeli, ja l\u00e4mp\u00f6menetelm\u00e4t, jotka nostavat v\u00e4liaikaisesti kivesten l\u00e4mp\u00f6tilaa v\u00e4hent\u00e4\u00e4kseen siitti\u00f6iden tuotantoa. L\u00e4\u00e4ketieteelliseen sertifiointiin ja rahoitukseen liittyvist\u00e4 haasteista huolimatta kiinnostus miesten ehk\u00e4isy\u00e4 kohtaan kasvaa maailmanlaajuisten tutkimusten ja Gates-s\u00e4\u00e4ti\u00f6n kaltaisten j\u00e4rjest\u00f6jen tukemana. Ehk\u00e4isyvalmisteiden markkinoiden ennustetaan nousevan 44 miljardiin dollariin vuoteen 2030 menness\u00e4, mik\u00e4 korostaa sukupuolten v\u00e4lisen tasa-arvoisen syntyvyyden valvonnan muutosmahdollisuuksia. Tapahtuman osallistujat suhtautuvat optimistisesti miesten ehk\u00e4isyn tulevaisuuteen yksil\u00f6iden voimaannuttamiskeinona perhesuunnittelussa.",
    "news_url": "https://www.dw.com/en/male-contraception-a-growing-business-with-game-changers/a-70453644",
    "news_time": 1729438320.0,
    "news_categories": [
        "business"
    ],
    "news_source_lang": "fi",
    "news_group": -1
}