{
    "news_source": "bbc",
    "news_id": "bbc_c4gpd2487e5o",
    "news_header": "Donald Trump voittaa presidentinvaalit 50,8 % \u00e4\u00e4nist\u00e4, her\u00e4tt\u00e4en huolia ja toiveita globaalisti h\u00e4nen ulkopoliittisista linjauksistaan, erityisesti Ukrainaan, Ven\u00e4j\u00e4\u00e4n ja Kiinaan.",
    "news_text": "Donald Trump, republikaanipuolueen ehdokas, voitti presidentinvaalit 72 631 585 \u00e4\u00e4nell\u00e4 (50,8 %), kun taas Kamala Harris, demokraattipuolueen ehdokas, sai 67 905 673 \u00e4\u00e4nt\u00e4 (47,5 %). H\u00e4nen voittonsa on her\u00e4tt\u00e4nyt maailmanlaajuisia reaktioita, erityisesti h\u00e4nen ulkopoliittisen linjansa suhteen, mik\u00e4 saattaa johtaa Yhdysvaltojen osallistumisen v\u00e4henemiseen globaaleissa konflikteissa. Ukrainassa tunteet Trumpin mahdollisista toimista ovat ristiriitaisia, ja jotkut pelk\u00e4\u00e4v\u00e4t Yhdysvaltojen tuen v\u00e4henemist\u00e4. Euroopan johtajat ovat huolissaan turvallisuus- ja kauppakysymyksist\u00e4. Israelissa Trumpin aiempi tuki otetaan vastaan my\u00f6nteisesti, mutta huolia on my\u00f6s Gazassa k\u00e4yt\u00e4v\u00e4n konfliktin suhteen. Kiina odottaa haastavaa kauppasuhdetta Trumpin presidenttikauden aikana. Yhteenvetona Trumpin voitto her\u00e4tt\u00e4\u00e4 kysymyksi\u00e4 kansainv\u00e4listen suhteiden tulevaisuudesta.",
    "news_url": "https://www.bbc.com/news/articles/c4gpd2487e5o",
    "news_time": 1730941980.0,
    "news_categories": [
        "world"
    ],
    "news_source_lang": "fi",
    "news_group": 178
}