{
    "news_source": "yle",
    "news_id": "yle_7420143424",
    "news_header": "Trump haastoi Twitterin, kun h\u00e4nen tilins\u00e4 j\u00e4\u00e4dytettiin Kapitolir\u00e4hin\u00f6iden j\u00e4lkeen vuonna 2021. Nykyisin X-niminen yritys on suostunut maksamaan h\u00e4nelle noin 10 miljoonaa dollaria korvauksena.",
    "news_original_title": "Elon Muskin X maksaa korvaukset Trumpille \u2013 osapuolet sopuun Trumpin nostamassa oikeusjutussa",
    "news_text": "Trump v\u00e4itti, ett\u00e4 h\u00e4nen sananvapauttaan rikottiin, kun h\u00e4nen tilins\u00e4 j\u00e4\u00e4dytettiin v\u00e4kivallan yllytt\u00e4misen riskin vuoksi. H\u00e4nen tilins\u00e4 palautettiin marraskuussa 2022 Elon Muskin ostaessa Twitterin ja muuttaessa sen nimeksi X. Lis\u00e4ksi Meta ilmoitti maksavansa 25 miljoonaa dollaria ratkaistakseen Trumpin kanssa liittyv\u00e4n oikeusjutun.",
    "news_url": "https://yle.fi/a/74-20143424",
    "news_time": 1739414760.0,
    "news_categories": [
        "world"
    ],
    "news_source_lang": "fi",
    "news_group": -1
}