{
    "news_source": "bbc",
    "news_id": "bbc_c77rg752nj7o",
    "news_header": "I\u00e4kk\u00e4 israelin mies, Shlomo Mansour, kuoli Hamasin hy\u00f6kk\u00e4yksess\u00e4 7. lokakuuta 2023, ja h\u00e4nen ruumiinsa pidet\u00e4\u00e4n panttivankina Gazassa.",
    "news_original_title": "Elderly hostage in Gaza was killed in 7 October attack, Israel says",
    "news_text": "Shlomo Mansour, 86-vuotias israelilainen mies, kuoli Hamasin hy\u00f6kk\u00e4yksess\u00e4 Etel\u00e4-Israelissa 7. lokakuuta 2023. H\u00e4nen ruumiinsa pidet\u00e4\u00e4n t\u00e4ll\u00e4 hetkell\u00e4 panttivankina Gazassa. Mansour kidnappattiin Kibbutz Kissufimist\u00e4, kun h\u00e4nen vaimonsa onnistui pakenemaan. Israelin armeija vahvisti h\u00e4nen kuolemansa tiedustelutietojen perusteella ja sanoi, ett\u00e4 h\u00e4nen nimens\u00e4 on panttivankien listalla, jotka Hamasin on m\u00e4\u00e4r\u00e4 vapauttaa. K\u00e4ynniss\u00e4 oleva panttivankitilanne on johtanut 16 israelilaisen panttivangin vapauttamiseen palestiinalaisvankien vaihdossa, mutta j\u00e4nnitteet kasvavat, kun Hamas uhkaa lyk\u00e4t\u00e4 lis\u00e4vapautuksia, ellei tiettyj\u00e4 ehtoja t\u00e4ytet\u00e4. Israelin hallitus on p\u00e4\u00e4tt\u00e4nyt palauttaa kaikki panttivangit, el\u00e4v\u00e4t tai kuolleet.",
    "news_url": "https://www.bbc.com/news/articles/c77rg752nj7o",
    "news_time": 1739267340.0,
    "news_categories": [
        "world"
    ],
    "news_source_lang": "fi",
    "news_group": -1
}