{
    "news_source": "bbc",
    "news_id": "bbc_ce85wx9jjndo",
    "news_header": "Sir Keir Starmerin teko\u00e4lysuunnitelma voi rasittaa Yhdistyneen kuningaskunnan juomavesivarantoja, koska datakeskukset tarvitsevat merkitt\u00e4v\u00e4sti vett\u00e4 j\u00e4\u00e4hdytt\u00e4miseen, mik\u00e4 her\u00e4tt\u00e4\u00e4 kest\u00e4vyysongelmia.",
    "news_original_title": "Concern UK's AI ambitions could lead to water shortages",
    "news_text": "Sir Keir Starmerin tavoite tehd\u00e4 Yhdistynyt kuningaskunta teko\u00e4lyn johtajaksi voi pahentaa olemassa olevia vesivarantojen ongelmia, sill\u00e4 datakeskukset vaativat suuria m\u00e4\u00e4ri\u00e4 vett\u00e4 j\u00e4\u00e4hdytt\u00e4miseen. Vaikka teknologiasektori kehitt\u00e4\u00e4 tehokkaampia j\u00e4rjestelmi\u00e4, hallitus tunnustaa kest\u00e4vyyshaasteet. Uudet datakeskukset suunnitellaan alueille, joilla on jo vesipulaa ilmastonmuutoksen vuoksi. Royal Academy of Engineering kehottaa tarkkoihin vesik\u00e4ytt\u00f6raportteihin teknologiayrityksilt\u00e4 ja korostaa kest\u00e4vien k\u00e4yt\u00e4nt\u00f6jen tarvetta ymp\u00e4rist\u00f6n vahingoittamisen v\u00e4ltt\u00e4miseksi. Paikallinen vastustus datakeskuksia kohtaan kasvaa maailmanlaajuisesti, ja vesiyhti\u00f6t tarkastelevat politiikkojaan n\u00e4iden vaatimusten valossa.",
    "news_url": "https://www.bbc.com/news/articles/ce85wx9jjndo",
    "news_time": 1738885680.0,
    "news_categories": [
        "science"
    ],
    "news_source_lang": "fi",
    "news_group": -1
}