{
    "news_source": "nasdaq",
    "news_id": "nasdaq_c36cc0ee8b12",
    "news_header": "Wall Streetin analyytikot suosittelevat Celsius Holdings Inc.:t\u00e4 (CELH) vahvasti ostettavaksi, mutta sijoittajien tulisi olla varovaisia, sill\u00e4 v\u00e4litt\u00e4j\u00e4suositukset eiv\u00e4t aina heijasta osakkeen todellista potentiaalia.",
    "news_original_title": "Wall Street Bulls Look Optimistic About Celsius (CELH): Should You Buy?",
    "news_text": "Sijoittajat luottavat usein Wall Streetin analyytikoiden suosituksiin ennen osakep\u00e4\u00e4t\u00f6ksi\u00e4. Celsius Holdings Inc.:ll\u00e4 (CELH) on keskim\u00e4\u00e4r\u00e4inen v\u00e4litt\u00e4j\u00e4suositus 1,67, mik\u00e4 viittaa vahvaan ostoon. Kuitenkin tutkimukset osoittavat, ett\u00e4 v\u00e4litt\u00e4j\u00e4suositukset eiv\u00e4t v\u00e4ltt\u00e4m\u00e4tt\u00e4 ohjaa sijoittajia tehokkaasti, usein analyytikoiden puolueellisuuden vuoksi, joka johtuu heid\u00e4n yritystens\u00e4 intresseist\u00e4. Zacks Rank, joka perustuu tulosennusteiden tarkistuksiin, on luotettavampi indikaattori osakkeen suorituskyvyst\u00e4. T\u00e4ll\u00e4 hetkell\u00e4 Celsiusilla on Zacks Rank #4 (Myy) heikentyneiden tulosennusteiden vuoksi, mik\u00e4 viittaa varovaisuuteen huolimatta positiivisesta v\u00e4litt\u00e4j\u00e4n\u00e4kemyksest\u00e4.",
    "news_url": "https://www.nasdaq.com/articles/wall-street-bulls-look-optimistic-about-celsius-celh-should-you-buy-0",
    "news_time": 1739190600.0,
    "news_categories": [
        "business",
        "tech"
    ],
    "news_source_lang": "fi",
    "news_group": 183
}