{
    "news_source": "yle",
    "news_id": "yle_7420136762",
    "news_header": "Tokmann ja Spar tekev\u00e4t yhteisty\u00f6t\u00e4 parantaakseen ruokatarjontaa Suomessa.",
    "news_text": "Tokmann tekee yhteisty\u00f6t\u00e4 Sparin kanssa haastamaan ruokakauppamarkkinoita Suomessa, alkaen t\u00e4st\u00e4 vuodesta. Kumppanuus tuo Sparin br\u00e4ndin Tokmanni-kauppoihin, mik\u00e4 laajentaa tuoretuotteiden myynti\u00e4. Tokmannin tavoitteena on perustaa uusi ruokaketju, joka kilpailee suurten toimijoiden, kuten Kesko, S-ryhm\u00e4 ja Lidl, kanssa, jotka t\u00e4ll\u00e4 hetkell\u00e4 hallitsevat yli 90 % markkinoista. Ensimm\u00e4inen Spar-ruokatoimisto avataan ensi kes\u00e4n\u00e4, ja lis\u00e4\u00e4 kauppoja on suunnitteilla sek\u00e4 mahdollisia itsen\u00e4isi\u00e4 Spar-lokaatioita tulevaisuudessa.",
    "news_url": "https://yle.fi/a/74-20136762",
    "news_time": 1736841660.0,
    "news_categories": [
        "business"
    ],
    "news_source_lang": "fi",
    "news_group": -1
}