{
    "news_source": "sn",
    "news_id": "sn_3145292",
    "news_header": "Uudet tutkimukset osoittavat, ett\u00e4 miesten hyttyset voivat juoda verta alhaisissa kosteusolosuhteissa ja haastaa uskomuksen, ett\u00e4 vain naiset sy\u00f6v\u00e4t verta.",
    "news_text": "Viimeaikaiset kokeet osoittavat, ett\u00e4 miesten hyttyset, tyypillisesti tunnettu ruokinta nektarilla, voivat my\u00f6s kuluttaa verta, kun kosteus on alhainen ja sokerin l\u00e4hteet ovat niukat. Penn Staten tutkijat kertovat, ett\u00e4 miesten hyttyset, kuten Culex tarsalis ja Aedes aegypti, voivat ruokkia verta, vaikkakin rajoitetuissa olosuhteissa. Vaikka miesten hyttysi\u00e4 yleens\u00e4 puuttuu kyky piirt\u00e4\u00e4 verta johtuen niiden suukappaleita, nesteytettyj\u00e4 miehi\u00e4 on havaittu poistaa verta haavoista. Vaikka tutkijat ep\u00e4ilev\u00e4t, ett\u00e4 miehet merkitt\u00e4v\u00e4sti edist\u00e4\u00e4 sairauksien siirtymist\u00e4, t\u00e4m\u00e4 tutkimus nopeuttaa miesten hyttysten roolin uudelleenarviointia veren ruokinnassa ja mahdollisten virusten levi\u00e4misess\u00e4.",
    "news_url": "https://www.sciencenews.org/article/male-mosquitoes-blood-disease",
    "news_time": 1729857600.0,
    "news_categories": [
        "science"
    ],
    "news_source_lang": "fi",
    "news_group": -1
}