{
    "news_source": "dw",
    "news_id": "dw_a71591784",
    "news_header": "Pommi-isku Afganistanin kaupunkikehitys- ja asuntoministeri\u00f6n alueella tappoi yhden ja haavoitti kolmea. Mies yritti hy\u00f6k\u00e4t\u00e4, mutta vartijat ampuivat h\u00e4net ennen kuin h\u00e4n p\u00e4\u00e4si tavoitteeseensa.",
    "news_original_title": "Afghanistan: Apparent suicide blast targets ministry complex",
    "news_text": "Kukaan ryhm\u00e4 ei ole ottanut vastuuta, mutta isku tapahtui kahden p\u00e4iv\u00e4n kuluttua islamilaisen valtion pommi-iskusta, jossa kuoli viisi.",
    "news_url": "https://www.dw.com/en/afghanistan-apparent-suicide-blast-targets-ministry-complex/a-71591784",
    "news_time": 1739432160.0,
    "news_categories": [
        "world"
    ],
    "news_source_lang": "fi",
    "news_group": 299
}