{
    "news_source": "yle",
    "news_id": "yle_7420122171",
    "news_header": "Kaksi loukkaantui v\u00e4kivaltaisessa riidassa junassa Pariisin l\u00e4hell\u00e4.",
    "news_text": "V\u00e4kivaltainen riita tapahtui junassa Pariisin ulkopuolella, mik\u00e4 johti kahteen loukkaantumiseen. Tapauksessa oli nelj\u00e4 haavaa, ja ep\u00e4ilty iski yht\u00e4 uhri\u00e4 k\u00e4sivarteen. V\u00e4kivalta tapahtui Ozoir-la-Ferri\u00e8re -asemalla, kun juna oli pys\u00e4htynyt laiturille.",
    "news_url": "https://yle.fi/a/74-20122171",
    "news_time": 1730704380.0,
    "news_categories": [
        "world"
    ],
    "news_source_lang": "fi",
    "news_group": -1
}