{
    "news_source": "bbc",
    "news_id": "bbc_c8r5ld8jvlzo",
    "news_header": "NASA:n astronautti Suni Williams teki avaruusk\u00e4velyn oltuaan ISS:ll\u00e4 seitsem\u00e4n kuukautta, odottaen viiv\u00e4stynytt\u00e4 paluutaan Maahan teknisten ongelmien vuoksi.",
    "news_original_title": "Nasa astronaut stuck in space ventures outside",
    "news_text": "NASA:n astronautti Suni Williams ja Butch Wilmore suorittivat avaruusk\u00e4velyn Kansainv\u00e4lisell\u00e4 avaruusasemalla (ISS) seitsem\u00e4n kuukauden oleskelun j\u00e4lkeen. Heid\u00e4n paluunsa Maahan on viiv\u00e4stynyt maaliskuun loppuun tai huhtikuuhun 2024 teknisten ongelmien vuoksi avaruusaluksessa. Kuuden tunnin avaruusk\u00e4velyn aikana Williams ja astronautti Nick Hague suorittivat huoltoteht\u00e4vi\u00e4, mukaan lukien laitteiden korjauksia ja valmisteluja tulevia t\u00f6it\u00e4 varten Alpha Magnetic Spectrometerissa. Williamsilla on suunniteltu toinen avaruusk\u00e4vely 23. tammikuuta 2024. Viiv\u00e4styksist\u00e4 huolimatta astronautit jatkavat ty\u00f6t\u00e4\u00e4n ISS:ll\u00e4.",
    "news_url": "https://www.bbc.com/news/articles/c8r5ld8jvlzo",
    "news_time": 1737101580.0,
    "news_categories": [
        "science"
    ],
    "news_source_lang": "fi",
    "news_group": -1
}