{
    "news_source": "bbc",
    "news_id": "bbc_c4gplnlq7zyo",
    "news_header": "Ex-Abercrombie & Fitch toimitusjohtaja Mike Jeffries ei ole syyllinen seksikauppaan ja prostituutiosyytteisiin.",
    "news_text": "Abercrombie & Fitchin entinen toimitusjohtaja Mike Jeffries ei ole syyllistynyt syytteeseen seksikaupasta ja valtioiden v\u00e4lisest\u00e4 prostituutiosta. H\u00e4nen v\u00e4itetty keskimm\u00e4inen James Jacobson oli my\u00f6s syyt\u00f6n. Jeffriesin yhteisty\u00f6kumppani Matthew Smith joutuu vastaaviin syytteisiin ja h\u00e4nen odotetaan saapuvan my\u00f6hemmin oikeuteen. Liittovaltion syytt\u00e4j\u00e4t v\u00e4itt\u00e4v\u00e4t, ett\u00e4 miehet harjoittavat v\u00e4kivaltaisia ja hyv\u00e4ksik\u00e4ytt\u00e4vi\u00e4 seksuaalisia tekoja k\u00e4ytt\u00e4en voimaa ja pakkoa. FBI:n tutkintaa syytettiin BBC:n raportista, jossa kerrottiin useiden miesten syyt\u00f6ksist\u00e4, jotka v\u00e4ittiv\u00e4t hyv\u00e4ksik\u00e4yt\u00f6n Jeffriesin ja Smithin is\u00e4nn\u00f6imiss\u00e4 tapahtumissa. Jeffries on kotiarestissa ja on julkaissut 10 miljoonan dollarin joukkovelkakirjalainan. Jos tuomitaan, miehet voivat joutua vankeuteen. Toimitusjohtajana vuosina 1992\u20132014 toiminut Jeffries on suunniteltu toiseen oikeudenk\u00e4yntiin 12. joulukuuta.",
    "news_url": "https://www.bbc.com/news/articles/c4gplnlq7zyo",
    "news_time": 1729879800.0,
    "news_categories": [
        "world"
    ],
    "news_source_lang": "fi",
    "news_group": -1
}