{
    "news_source": "yle",
    "news_id": "yle_7420144626",
    "news_header": "Putin ja Trump saattavat tavata helmikuussa; Yhdysvaltojen ja Ven\u00e4j\u00e4n suhteet tarvitsevat elvytt\u00e4mist\u00e4.",
    "news_original_title": "Peskov: Putin ja Trump saattavat tavata helmikuussa",
    "news_text": "Ven\u00e4j\u00e4n presidentti Vladimir Putin ja Yhdysvaltain presidentti Donald Trump saattavat tavata helmikuun loppuun menness\u00e4. Dmitri Peskov totesi, ett\u00e4 valmistelu vie aikaa. Trump viittasi mahdolliseen tapaamiseen helmikuussa. Peskov mainitsi, ett\u00e4 Yhdysvaltojen ja Ven\u00e4j\u00e4n ulkoministerien \u00e4skett\u00e4inen tapaaminen Saudi-Arabiassa oli ratkaiseva askel Ukrainan kriisin ratkaisemiseksi, keskittyen kahdenv\u00e4lisiin suhteisiin. H\u00e4n korosti Yhdysvaltojen ja Ven\u00e4j\u00e4n suhteiden elvytt\u00e4misen tarvetta.",
    "news_url": "https://yle.fi/a/74-20144626",
    "news_time": 1739954160.0,
    "news_categories": [
        "world"
    ],
    "news_source_lang": "fi",
    "news_group": -1,
    "keywords": [
        "russian_invasion_4546",
        "russia",
        "foreign",
        "donald_trump",
        "vladimir_putin",
        "united_states",
        "ukraine"
    ]
}