{
    "news_source": "bbc",
    "news_id": "bbc_cvgdrqgxyg3o",
    "news_header": "Kiinalainen helikopteri lensi l\u00e4hell\u00e4 Filippiinien lentokonetta; protesti odotettavissa.",
    "news_original_title": "Chinese navy helicopter flies &#x27;dangerously&#x27; close to Philippine plane",
    "news_text": "Kiinalainen laivaston helikopteri lensi vaarallisen l\u00e4helle Filippiinien lentokonetta kiistellyll\u00e4 alueella Etel\u00e4-Kiinan merell\u00e4, mik\u00e4 sai Filippiinien hallituksen tekem\u00e4\u00e4n virallisen protestin. Tapahtuma tapahtui Scarboroughin riutalla, jota on kiistetty vuodesta 2012. Samaan aikaan Intian Kumbh Melassa pel\u00e4t\u00e4\u00e4n uhreja, ja Etel\u00e4-Koreassa poliittinen levottomuus jatkuu virkasyyt\u00f6sten my\u00f6t\u00e4.",
    "news_url": "https://www.bbc.com/news/videos/cvgdrqgxyg3o",
    "news_time": 1739938920.0,
    "news_categories": [
        "world"
    ],
    "news_source_lang": "fi",
    "news_group": -1,
    "keywords": []
}