{
    "news_source": "bbc",
    "news_id": "bbc_cx2kv219d2go",
    "news_header": "Georgian tuomari on est\u00e4nyt seitsem\u00e4n Trumpin suosimaa vaalis\u00e4\u00e4nt\u00f6\u00e4, jotka viittaavat \u00e4\u00e4nestysprosessiin.",
    "news_text": "Fulton County Superior Court Tuomari Thomas Cox hallitsi Georgiassa seitsem\u00e4\u00e4 uutta vaalis\u00e4\u00e4nt\u00f6\u00e4, joita republikaani Donald Trump tukee, ja totesi, ett\u00e4 se h\u00e4iritsi lainvastaisesti \u00e4\u00e4nestysprosessia. Esitetyist\u00e4 s\u00e4\u00e4nn\u00f6ist\u00e4 oli edellytys k\u00e4sien laskennalle, jonka kriitikot v\u00e4ittiv\u00e4t viiv\u00e4stytt\u00e4v\u00e4n tuloksia. \u00c4\u00e4nestys Georgiassa on ollut enn\u00e4tysm\u00e4\u00e4r\u00e4, sill\u00e4 ensimm\u00e4isin\u00e4 p\u00e4ivin\u00e4 \u00e4\u00e4nestettiin yli 459 000. P\u00e4\u00e4t\u00f6s on k\u00e4ynniss\u00e4 olevien oikeudellisten haasteiden keskell\u00e4, joita Trump on kohdannut pyrkiess\u00e4\u00e4n kumoamaan vuoden 2020 vaalitulokset. Tuomari korosti, ett\u00e4 vaaliprosessin ep\u00e4varmuuden lis\u00e4\u00e4minen on haitallista kansalaisten luottamukselle.",
    "news_url": "https://www.bbc.com/news/articles/cx2kv219d2go",
    "news_time": 1729122060.0,
    "news_categories": [
        "world"
    ],
    "news_source_lang": "fi",
    "news_group": -1
}