{
    "news_source": "nasdaq",
    "news_id": "nasdaq_082a4d588b8b",
    "news_header": "International Paper Ilmestyy nelj\u00e4n US Facilities; Vaikutus 674 ty\u00f6paikkaa",
    "news_original_title": "International Paper Announces Closure Of 4 US Facilities; To Impact 674 Jobs",
    "news_text": "",
    "news_url": "https://www.nasdaq.com/articles/international-paper-announces-closure-4-us-facilities-impact-674-jobs",
    "news_time": 1739453100.0,
    "news_categories": [
        "business",
        "markets"
    ],
    "news_source_lang": "fi",
    "news_group": -1
}