{
    "news_source": "yle",
    "news_id": "yle_7420143913",
    "news_header": "Lauantaina Israel aikoo vapauttaa 369 palestiinalaista vankia, kun taas Hamasin odotetaan vapauttavan kolme israelilaista panttivankia osana tulitaukosopimusta. T\u00e4m\u00e4 on kuudes vankien vaihto tulitauon alkamisen j\u00e4lkeen 19.",
    "news_original_title": "Hamas vapauttaa kolme israelilaista panttivankia",
    "news_text": "tammikuuta. Tulitauon jatkuminen oli ep\u00e4varmaa aiemmin t\u00e4ll\u00e4 viikolla, kun Hamas uhkasi j\u00e4\u00e4dytt\u00e4\u00e4 panttivankien vapauttamisen Israelin v\u00e4itettyjen rikkomusten vuoksi, mik\u00e4 puolestaan uhkasi aloittaa taistelut uudelleen. Kuitenkin molemmat osapuolet ovat p\u00e4\u00e4tt\u00e4neet jatkaa tulitaukosopimuksen toteuttamista, ja neuvottelut seuraavasta vaiheesta ovat k\u00e4ynniss\u00e4.",
    "news_url": "https://yle.fi/a/74-20143913",
    "news_time": 1739599620.0,
    "news_categories": [
        "world"
    ],
    "news_source_lang": "fi",
    "news_group": 341
}