{
    "news_source": "dw",
    "news_id": "dw_a70580848",
    "news_header": "Andrei, en vitrysk politisk flykting och konstn\u00e4r, s\u00f6ker asyl i Bulgarien med sin man Alex, en journalist inf\u00f6r f\u00f6rf\u00f6ljelse i Ryssland. Deras asylans\u00f6kan st\u00e5r inf\u00f6r utmaningar p\u00e5 grund av Bulgariens restriktiva lagar om HBTQ+-r\u00e4ttigheter.",
    "news_text": "Andrei, en 30-\u00e5rig politisk flykting och konstn\u00e4r fr\u00e5n Minsk, s\u00f6ker asyl i Bulgarien tillsammans med sin man Alex, en journalist som \u00e4r kritisk till Putin. De gifte sig i Danmark, eftersom samk\u00f6nade \u00e4ktenskap inte \u00e4r erk\u00e4nda i sina heml\u00e4nder, som har alltmer repressiva lagar mot HBTQ+ individer. Efter att ha f\u00e5tt hot i Ryssland s\u00f6kte de asyl i Bulgarien, men bara Alex fick det. Andreis ans\u00f6kan nekades p\u00e5 grund av p\u00e5st\u00e5enden om mots\u00e4gelsefulla uttalanden och brist p\u00e5 upplevd risk. Deras advokat h\u00e4vdar att Andrei st\u00e5r inf\u00f6r risker som Alex make. Trots att de k\u00e4nner sig tryggare i Bulgarien har de senaste lagarna som begr\u00e4nsar HBTQ+-r\u00e4ttigheter v\u00e4ckt oro f\u00f6r deras s\u00e4kerhet. De planerar att l\u00e4mna in sin asylans\u00f6kan och ta sitt \u00e4rende till Europadomstolen f\u00f6r m\u00e4nskliga r\u00e4ttigheter.",
    "news_url": "https://www.dw.com/en/gay-russo-belarusian-couple-seeks-asylum-in-bulgaria/a-70580848",
    "news_time": 1729911540.0,
    "news_categories": [
        "world"
    ],
    "news_source_lang": "sv",
    "news_group": -1
}