{
    "news_source": "yle",
    "news_id": "yle_7420120575",
    "news_header": "V\u00e4rldsmeteorologiska Organisationen rapporterar en betydande \u00f6kning av v\u00e4xthusgaskoncentrationerna, s\u00e4rskilt koldioxid, som har \u00f6kat med \u00f6ver 10% under tv\u00e5 decennier, n\u00e5r niv\u00e5er som inte setts i miljontals \u00e5r.",
    "news_text": "Enligt en rapport fr\u00e5n World Meteorological Organization (WMO) har atmosf\u00e4riska koldioxidkoncentrationer \u00f6kat med \u00f6ver 10% under de senaste tv\u00e5 decennierna, med niv\u00e5er 2023 n\u00e5r 420,0 ppm, en 51% \u00f6kning sedan 1750. Denna \u00f6kning beror till stor del p\u00e5 anv\u00e4ndning av fossila br\u00e4nslen och cementproduktion. De nuvarande CO2-niv\u00e5erna \u00e4r j\u00e4mf\u00f6rbara med de fr\u00e5n 3-5 miljoner \u00e5r sedan n\u00e4r globala temperaturer var 2-3 grader h\u00f6gre. Medan utsl\u00e4ppen har stabiliserats kvarst\u00e5r de l\u00e5ngsiktiga effekterna av CO2 i atmosf\u00e4ren, eftersom det kan kvarst\u00e5 i tusentals \u00e5r. Rapporten betonar ocks\u00e5 att utsl\u00e4pp fr\u00e5n stora vegetationsbr\u00e4nder och minskade kols\u00e4nkor i skogen har bidragit till \u00f6kningen av koldioxidniv\u00e5erna.",
    "news_url": "https://yle.fi/a/74-20120575",
    "news_time": 1730100780.0,
    "news_categories": [
        "world"
    ],
    "news_source_lang": "sv",
    "news_group": 109
}