{
    "news_source": "bbc",
    "news_id": "bbc_c4g949m4g41o",
    "news_header": "En man b\u00f6tf\u00e4lldes med 200 euro f\u00f6r att ha anv\u00e4nt h\u00f6gtalartelefon p\u00e5 en fransk t\u00e5gstation och \u00f6verklagar b\u00f6tesbeloppet.",
    "news_original_title": "Man launches fight against fine for loudspeaker call at French station",
    "news_text": "David, en 54-\u00e5rig man, b\u00f6tf\u00e4lldes med 200 euro p\u00e5 Nantes station i Frankrike f\u00f6r att ha gjort ett samtal med h\u00f6gtalartelefon. Han fick f\u00f6rst veta att han skulle b\u00f6tf\u00e4llas med 150 euro, men beloppet \u00f6kade n\u00e4r han inte betalade omedelbart. SNCF, j\u00e4rnv\u00e4gsf\u00f6retaget, bekr\u00e4ftade b\u00f6tesbeloppet och uppgav att deras s\u00e4kerhetspersonal har r\u00e4tt att utf\u00e4rda s\u00e5dana b\u00f6ter. \u00c4ven om det inte finns n\u00e5gon nationell lag i Frankrike som f\u00f6rbjuder anv\u00e4ndning av h\u00f6gtalartelefon p\u00e5 offentliga platser, finns det regler f\u00f6r ljudniv\u00e5er. Offentlig opinion ogillar generellt h\u00f6gljudda telefonsamtal, vilket leder till olika regler i olika l\u00e4nder ang\u00e5ende telefonanv\u00e4ndning p\u00e5 kollektivtrafik.",
    "news_url": "https://www.bbc.com/news/articles/c4g949m4g41o",
    "news_time": 1738873260.0,
    "news_categories": [
        "world"
    ],
    "news_source_lang": "sv",
    "news_group": -1
}