{
    "news_source": "yle",
    "news_id": "yle_7420122685",
    "news_header": "Donald Trump tackade Finland f\u00f6r dess st\u00f6d i Afghanistan, men fick ocks\u00e5 konstiga kommentarer om landet. Deras relation n\u00e5dde sin h\u00f6jdpunkt under toppm\u00f6tet i Helsingfors 2018 med Putin.",
    "news_text": "Donald Trump tackade Finland f\u00f6r dess hj\u00e4lp i Afghanistan och erk\u00e4nde landets st\u00f6d f\u00f6r den USA-ledda koalitionen. Deras relation n\u00e5dde sin h\u00f6jdpunkt under toppm\u00f6tet i Helsingfors 2018 med den ryska presidenten Vladimir Putin. Trump har genom \u00e5ren gjort olika kommentarer om Finland, inklusive fr\u00e5gor om landets sj\u00e4lvst\u00e4ndighet och diskussioner om skogsf\u00f6rvaltningsmetoder. Han n\u00e4mnde ocks\u00e5 Finlands effektiva hantering av skogsbr\u00e4nder som en modell under ett bes\u00f6k i Kalifornien.",
    "news_url": "https://yle.fi/a/74-20122685",
    "news_time": 1730912460.0,
    "news_categories": [
        "world"
    ],
    "news_source_lang": "sv",
    "news_group": 175
}