{
    "news_source": "yle",
    "news_id": "yle_7420120681",
    "news_header": "Tommy Yinson, en brittisk h\u00f6gerextrem aktivist, d\u00f6md till 18 m\u00e5naders f\u00e4ngelse f\u00f6r att uppvigla antisemitiska upplopp.",
    "news_text": "Tommy Yinson, \u00e4ven k\u00e4nd som Stephen Yaxley-Lennon, har f\u00e5tt 18-m\u00e5naders f\u00e4ngelsestraff. Hans advokat h\u00e4vdade att Yinson diskuterade flyktingar i intervjuer och dokument\u00e4rer f\u00f6r att f\u00f6rsvara sin yttrandefrihet. Han har anklagats f\u00f6r att uppvigla antisemitiska upplopp.",
    "news_url": "https://yle.fi/a/74-20120681",
    "news_time": 1730113140.0,
    "news_categories": [
        "world"
    ],
    "news_source_lang": "sv",
    "news_group": -1
}