{
    "news_source": "sn",
    "news_id": "sn_3145297",
    "news_header": "Kriminalteknisk entomologi anv\u00e4nds i Sydafrika f\u00f6r att bek\u00e4mpa nosh\u00f6rning genom att uppskatta d\u00f6dstiden genom insektsbevis.",
    "news_text": "I Sydafrika st\u00f6der r\u00e4ttsmedicinsk entomologi i kampen mot nosh\u00f6rning genom att l\u00e5ta utredare uppskatta tiden f\u00f6r d\u00f6den av poachade nosh\u00f6rningar med hj\u00e4lp av insektsbevis. Denna metod, som inneb\u00e4r att samla in insekter som bl\u00e5sflugor och skalbaggar fr\u00e5n slaktkropparna, hj\u00e4lper till att skapa ett minimum postmortem intervall, vilket hj\u00e4lper till att sp\u00e5ra och d\u00f6ma poachers. Tekniken anpassades fr\u00e5n m\u00e4nskliga r\u00e4ttsmedicinska unders\u00f6kningar och har visat l\u00f6fte i \u00f6kande nosh\u00f6rningar genom f\u00f6rb\u00e4ttrade anti-poaching anstr\u00e4ngningar. Trots dess effektivitet, \u00e4r r\u00e4ttsmedicinsk entomologi inte allm\u00e4nt anv\u00e4nds i vilda brottsutredningar.",
    "news_url": "https://www.sciencenews.org/article/insects-help-catch-rhino-poachers",
    "news_time": 1729771200.0,
    "news_categories": [
        "science"
    ],
    "news_source_lang": "sv",
    "news_group": -1
}