{
    "news_source": "bbc",
    "news_id": "bbc_cp82jvd3g54o",
    "news_header": "Detaljhandelsbrott \u00f6kar, med butikstjuvar som utf\u00f6r alltmer dj\u00e4rva och v\u00e5ldsamma st\u00f6lder utan r\u00e4dsla f\u00f6r konsekvenser, enligt British Retail Consortium.",
    "news_original_title": "Shoplifters 'out of control' and becoming more brazen, say retailers",
    "news_text": "Detaljhandelsbrott har \u00f6kat i Storbritannien, med butikstjuvar som nu g\u00f6r \u00f6ver 20 miljoner st\u00f6lder som kostar detaljhandeln 2 miljarder pund. British Retail Consortium rapporterar en \u00f6kning p\u00e5 50 procent av v\u00e5ld mot butikspersonal, d\u00e4r m\u00e5nga brottslingar agerar \u00f6ppet inf\u00f6r kunder. Polisens statistik visar en \u00f6kning p\u00e5 23 procent av butikstjuveri, den h\u00f6gsta siffran sedan 2003. \u00c5terf\u00f6rs\u00e4ljare uppmanas att rapportera incidenter, men m\u00e5nga g\u00f6r det inte p\u00e5 grund av bristande respons. Regeringen uppmanas att vidta \u00e5tg\u00e4rder, inklusive att skapa ett specifikt brott f\u00f6r att angripa detaljhandelsarbetare.",
    "news_url": "https://www.bbc.com/news/articles/cp82jvd3g54o",
    "news_time": 1738229700.0,
    "news_categories": [
        "business"
    ],
    "news_source_lang": "sv",
    "news_group": -1
}