{
    "news_source": "bbc",
    "news_id": "bbc_clyv2eryp6vo",
    "news_header": "En teashop\u00e4gare i Somerset uppmanar f\u00f6rbundskanslern att \u00e4ndra momsregler som hindrar sm\u00e5f\u00f6retag fr\u00e5n att v\u00e4xa.",
    "news_text": "Steve Corrick, \u00e4gare av en liten teskop i Somerset, har uppmanat f\u00f6rbundskanslern att revidera momsregler som tvingar honom att begr\u00e4nsa sitt kaf\u00e9s driftdagar f\u00f6r att undvika att \u00f6verstiga \u00a3 90.000 oms\u00e4ttning tr\u00f6skel. Att \u00f6verskrida denna gr\u00e4ns skulle kr\u00e4va att han tar ut moms p\u00e5 all f\u00f6rs\u00e4ljning, vilket g\u00f6r verksamheten ekonomiskt oundviklig. Han h\u00e4vdar att den nuvarande skattestrukturen, ofta kallad klippkanten, avskr\u00e4cker sm\u00e5f\u00f6retag fr\u00e5n att v\u00e4xa. En unders\u00f6kning av Federation of Small Businesses visade att m\u00e5nga f\u00f6retag st\u00e5r inf\u00f6r liknande utmaningar p\u00e5 grund av dessa regler. Corrick betonar behovet av reformer f\u00f6r att st\u00f6dja sm\u00e5f\u00f6retag och hindra dem fr\u00e5n att h\u00e5llas tillbaka.",
    "news_url": "https://www.bbc.com/news/articles/clyv2eryp6vo",
    "news_time": 1730174940.0,
    "news_categories": [
        "business"
    ],
    "news_source_lang": "sv",
    "news_group": -1
}