{
    "news_source": "bbc",
    "news_id": "bbc_cze3yr77j9wo",
    "news_header": "Donald Trump vinner valet med 72 631 585 r\u00f6ster (50,8%) mot Kamala Harris som fick 67 905 673 r\u00f6ster (47,5%).",
    "news_text": "Donald Trump har uppn\u00e5tt en avg\u00f6rande seger \u00f6ver Kamala Harris i det senaste valet, d\u00e4r han fick 72 631 585 r\u00f6ster (50,8%) j\u00e4mf\u00f6rt med Harris 67 905 673 r\u00f6ster (47,5%). Trumps framg\u00e5ng st\u00f6ddes av starkt st\u00f6d fr\u00e5n vita arbetarklassv\u00e4ljare, en betydande \u00f6kning av latino-r\u00f6ster och f\u00f6rb\u00e4ttrad prestation bland yngre v\u00e4ljare. Han vann viktiga battleground-stater som Pennsylvania, Michigan och Wisconsin, som var avg\u00f6rande f\u00f6r demokraterna i det f\u00f6reg\u00e5ende valet. Trumps budskap om ekonomin, s\u00e4rskilt ang\u00e5ende inflation, resonerade med m\u00e5nga v\u00e4ljare som k\u00e4nde sig besvikna \u00f6ver det demokratiska partiets hantering av ekonomiska fr\u00e5gor.",
    "news_url": "https://www.bbc.com/news/articles/cze3yr77j9wo",
    "news_time": 1730930880.0,
    "news_categories": [
        "world"
    ],
    "news_source_lang": "sv",
    "news_group": 178
}