{
    "news_source": "bbc",
    "news_id": "bbc_c238kv8ddeyo",
    "news_header": "Arkeologer uppt\u00e4ckte tv\u00e5 medeltida st\u00e4der i \u00f6stra Uzbekistan, utmanande tidigare \u00f6vertygelser om Silk Road handelsv\u00e4gar.",
    "news_text": "Arkeologer har avsl\u00f6jat resterna av tv\u00e5 medeltida st\u00e4der, Tugunbulak och Tashbulak, i bergen i \u00f6stra Uzbekistan, som kan f\u00f6r\u00e4ndra v\u00e5r f\u00f6rst\u00e5else av Sidenv\u00e4gen. Dessa st\u00e4der, bel\u00e4gna p\u00e5 h\u00f6ga h\u00f6jder, ans\u00e5gs vara livliga bos\u00e4ttningar mellan 8 och 11-talet. Uppt\u00e4ckten gjordes med hj\u00e4lp av fj\u00e4rranalys teknik, inklusive dr\u00f6nare och lidar, avsl\u00f6jar betydande arkitektoniska egenskaper och bevis p\u00e5 j\u00e4rnproduktion. Resultaten belyser den historiska betydelsen av h\u00f6gh\u00f6jd urbanism och sammankopplingar av forntida samh\u00e4llen i Centralasien.",
    "news_url": "https://www.bbc.com/news/articles/c238kv8ddeyo",
    "news_time": 1729818780.0,
    "news_categories": [
        "world"
    ],
    "news_source_lang": "sv",
    "news_group": -1
}