{
    "news_source": "bbc",
    "news_id": "bbc_c4gzd62g1r3o",
    "news_header": "Australien planerar att f\u00f6rbjuda barn under 16 \u00e5r fr\u00e5n sociala medier f\u00f6r att skydda deras s\u00e4kerhet online.",
    "news_text": "Australiens regering, ledd av premi\u00e4rminister Anthony Albanese, planerar att inf\u00f6ra lagstiftning som f\u00f6rbjuder barn under 16 \u00e5r fr\u00e5n sociala medier f\u00f6r att ta itu med oro kring online-s\u00e4kerhet. De f\u00f6reslagna lagarna, som ska diskuteras i parlamentet n\u00e4sta vecka, syftar till att minska den skada som sociala medier kan orsaka unga m\u00e4nniskor. F\u00f6rbudet kommer inte att p\u00e5verka dem som redan anv\u00e4nder sociala medier och det kommer inte att finnas n\u00e5gra undantag f\u00f6r f\u00f6r\u00e4ldrasamtycke. eSafety-kommission\u00e4ren kommer att \u00f6vervaka lagarna, som tr\u00e4der i kraft ett \u00e5r efter att de antas. Experter \u00e4r delade om effektiviteten av s\u00e5dana f\u00f6rbud, d\u00e4r vissa f\u00f6respr\u00e5kar s\u00e4kerhetsstandarder ist\u00e4llet. Intressegrupper har uttryckt oro \u00f6ver att f\u00f6rbudet kan vara f\u00f6r grovt, medan andra h\u00e4vdar att det \u00e4r n\u00f6dv\u00e4ndigt f\u00f6r att skydda barn fr\u00e5n skadligt inneh\u00e5ll online.",
    "news_url": "https://www.bbc.com/news/articles/c4gzd62g1r3o",
    "news_time": 1730933940.0,
    "news_categories": [
        "world"
    ],
    "news_source_lang": "sv",
    "news_group": -1
}