{
    "news_source": "sn",
    "news_id": "sn_3145339",
    "news_header": "Rediscovery av gigantisk laxkarp i Kambodja v\u00e4cker hopp om \u00f6verlevnad efter n\u00e4stan tv\u00e5 decennier av fr\u00e5nvaro.",
    "news_text": "Den j\u00e4tte laxkarp (Aaptosyax grypus), en kritiskt utrotningshotad art, har \u00e5teruppt\u00e4ckts i Kambodjas Mekong River efter att ha setts sedan 2005. Forskare bekr\u00e4ftade f\u00f6rekomsten av tre individer som f\u00e5ngats mellan 2020 och 2023, och reigniterade hopp om artens \u00f6verlevnad. \u00c5teruppt\u00e4ckten tyder p\u00e5 att karpen kan vara mer utbredd \u00e4n tidigare trott, vilket leder till att Kambodja l\u00e4gger till den i sin lista \u00f6ver skyddade arter. Men framtiden f\u00f6r arten f\u00f6rblir os\u00e4ker p\u00e5 grund av hot som livsmilj\u00f6st\u00f6rningar fr\u00e5n dammar, \u00f6verfiske och klimatf\u00f6r\u00e4ndringar. Forskare betonar att denna uppt\u00e4ckt \u00e4r avg\u00f6rande inte bara f\u00f6r karpen utan ocks\u00e5 f\u00f6r att skydda Mekongs ekosystem.",
    "news_url": "https://www.sciencenews.org/article/mekong-ghost-megafish-rediscovered",
    "news_time": 1729778400.0,
    "news_categories": [
        "science"
    ],
    "news_source_lang": "sv",
    "news_group": -1
}