{
    "news_source": "dw",
    "news_id": "dw_a70570272",
    "news_header": "Tyska f\u00f6retagsledare och politiker samlas i Indien f\u00f6r att st\u00e4rka ekonomiska band med Asien-Stillahavsomr\u00e5det mitt i geopolitiska f\u00f6r\u00e4ndringar och fokus p\u00e5 diversifiering fr\u00e5n Kina.",
    "news_text": "Topp tyska f\u00f6retagsledare och politiker bes\u00f6ker Indien f\u00f6r en betydande konferens som syftar till att f\u00f6rb\u00e4ttra ekonomiska relationer mellan Tyskland och Asien och Stillahavsomr\u00e5det, vilket \u00e5terspeglar regionens v\u00e4xande betydelse p\u00e5 grund av geopolitiska f\u00f6r\u00e4ndringar. Den Asien-Stillahavskonferensen kommer att sammanfalla med mellanstatliga samr\u00e5d mellan Tyskland och Indien, medordf\u00f6rande Olaf Scholz och premi\u00e4rminister Narendra Modi. Tysklands export till Asien-Stillahavsomr\u00e5det n\u00e5dde 214,6 miljarder euro \u00e5r 2023, och en ny studie visar en positiv syn p\u00e5 tyska f\u00f6retag i regionen, trots utmaningar i Kina. Indisk ekonomisk tillv\u00e4xt och gynnsamma investeringsf\u00f6rh\u00e5llanden lockar tyska f\u00f6retag, \u00e4ven om de st\u00e5r inf\u00f6r byr\u00e5kratiska och reglerande hinder. Sammantaget, medan diversifiering fr\u00e5n Kina, tyska f\u00f6retag f\u00f6rblir optimistiska om m\u00f6jligheter i Indien och andra Asien-Stillahavsmarknader.",
    "news_url": "https://www.dw.com/en/can-india-become-the-next-china-for-german-business/a-70570272",
    "news_time": 1729680000.0,
    "news_categories": [
        "business"
    ],
    "news_source_lang": "sv",
    "news_group": -1
}