{
    "news_source": "dw_science",
    "news_id": "dw_science_7070298947",
    "news_header": "CERN juhlii 70-vuotisjuhliaan ja on ollut keskeinen paikka tieteellisille l\u00e4pimurroille, kuten Higgsin bosonin l\u00f6yt\u00e4miselle.",
    "news_text": "Euroopan ydintutkimuskeskus CERN on ollut vuodesta 1954 l\u00e4htien merkitt\u00e4v\u00e4 tieteellinen keskus, jossa tuhannet tutkijat ovat ty\u00f6skennelleet universumin salaisuuksien parissa. CERN juhlii 70-vuotisjuhliaan 29. syyskuuta. Keskuksen tunnetuin laite on 27 kilometrin pituinen hiukkaskiihdytin, Suuri Hadronikiihdytin (LHC), joka on auttanut l\u00f6yt\u00e4m\u00e4\u00e4n Higgsin bosonin vuonna 2012. LHC:n avulla tutkijat pyrkiv\u00e4t ymm\u00e4rt\u00e4m\u00e4\u00e4n universumin perustavanlaatuisia kysymyksi\u00e4 ja kehitt\u00e4m\u00e4\u00e4n uusia teknologioita. Tulevaisuudessa kehitet\u00e4\u00e4n my\u00f6s 'toisen sukupolven' LHC:t\u00e4, joka mahdollistaa protonien t\u00f6rm\u00e4ysten m\u00e4\u00e4r\u00e4n lis\u00e4\u00e4misen merkitt\u00e4v\u00e4sti.",
    "news_url": "https://www.dw.com/en/cern-at-70-smashing-elementary-particles-for-humanity/a-70298947",
    "news_time": "2024/9/25/6/31",
    "news_primary_keyword": "hiukkasfysiikka"
}