{
    "news_source": "yle_world",
    "news_id": "yle_world_7420111973",
    "news_header": "Uuden komission salkkujaon julkistus viiv\u00e4styy",
    "news_text": "EU-komission puheenjohtaja Ursula von der Leyen saattaa kertoa tiistaina Strasbourgissa uuden komission salkkujaosta, jonka sis\u00e4lt\u00f6\u00e4 on viime hetkiin saakka hiottu. Alun perin salkkujaon piti tulla julki viime viikolla, mutta se siirrettiin. P\u00e4\u00e4ministeri Petteri Orpo on ilmaissut haluavansa Henna Virkkuselle kilpailukykyyn liittyv\u00e4n salkun. Julkistuksen j\u00e4lkeen komissaariehdokkaiden ja komission on saatava hyv\u00e4ksynt\u00e4 Euroopan parlamentilta syksyn aikana.",
    "news_url": "https://yle.fi/a/74-20111973",
    "news_time": "2024/9/16/22/8",
    "news_primary_keyword": "ursula von der leyen"
}