{
    "news_source": "dw_world",
    "news_id": "dw_world_70262349",
    "news_header": "FBI keskeytti kiinalaisen hakkeriryhm\u00e4n 'Flax Typhoon', joka hy\u00f6kk\u00e4si Yhdysvaltojen kriittiseen infrastruktuuriin.",
    "news_text": "FBI ilmoitti, ett\u00e4 se on keskeytt\u00e4nyt kiinalaisen hakkeriryhm\u00e4n, nimelt\u00e4\u00e4n 'Flax Typhoon', joka kohdisti hy\u00f6kk\u00e4yksi\u00e4 Yhdysvaltojen kriittiseen infrastruktuuriin. Ryhm\u00e4 asensi haittaohjelmia tuhansiin tietokoneisiin ja internet-yhteyksill\u00e4 varustettuihin laitteisiin, mik\u00e4 johti laajan botnetin syntymiseen. Kohteina olivat yliopistot, hallituksen virastot, telekommunikaatiopalveluntarjoajat, mediaorganisaatiot ja kansalaisj\u00e4rjest\u00f6t. FBI:n johtaja Chris Wray kertoi, ett\u00e4 ryhm\u00e4\u00e4 py\u00f6ritti kiinalainen yritys, Integrity Technology Group, joka toimi IT-yrityksen\u00e4 mutta my\u00f6s ker\u00e4si tiedustelutietoa Kiinan hallitukselle. Wray varoitti, ett\u00e4 Kiinan hallitus tulee jatkamaan hy\u00f6kk\u00e4yksi\u00e4 Yhdysvaltojen organisaatioita kohtaan. Kiinan suurl\u00e4hetyst\u00f6 Washingtonissa kiisti syyt\u00f6kset ja v\u00e4itti, ett\u00e4 Kiina torjuu kaikki kyberhy\u00f6kk\u00e4ykset.",
    "news_url": "https://www.dw.com/en/fbi-disrupts-major-chinese-hacking-group-director-says/a-70262349",
    "news_time": "2024/9/18/19/58",
    "news_primary_keyword": "kiinalainen hakkeriryhm\u00e4"
}