{
    "news_source": "yle_business",
    "news_id": "yle_business_7420112360",
    "news_header": "Suomen saunapresidentti kutsui Japanin saunakuninkaan tutustumaan suomalaisiin saunoihin.",
    "news_text": "Hiroshi Ota, Japanin saunakuningas, vieraili Suomessa tutustumassa saunakulttuuriin ja nauttimassa suomalaisista saunoista. H\u00e4n koki suomalaisen saunan ainutlaatuisuuden ja haluaa tuoda oppimaansa takaisin Japaniin. Kansainv\u00e4lisen saunaliiton presidentti Risto Elomaa korostaa, ett\u00e4 sauna el\u00e4\u00e4 buumia maailmalla, mutta Suomessa on hiljaista. Elomaa uskoo, ett\u00e4 suomalaisilla yrityksill\u00e4 on hyvi\u00e4 mahdollisuuksia menesty\u00e4 Japanin markkinoilla, jos ne ymm\u00e4rt\u00e4v\u00e4t paikallista saunomiskulttuuria.",
    "news_url": "https://yle.fi/a/74-20112360",
    "news_time": "2024/9/21/17/18",
    "news_primary_keyword": "sauna"
}